odoo/addons/l10n_es_subcontractor_certificate/README.rst
odoo/addons/l10n_es_subcontractor_certificate/__init__.py
odoo/addons/l10n_es_subcontractor_certificate/__manifest__.py
odoo/addons/l10n_es_subcontractor_certificate/i18n/bg.po
odoo/addons/l10n_es_subcontractor_certificate/i18n/ca.po
odoo/addons/l10n_es_subcontractor_certificate/i18n/cs.po
odoo/addons/l10n_es_subcontractor_certificate/i18n/en_US.po
odoo/addons/l10n_es_subcontractor_certificate/i18n/es.po
odoo/addons/l10n_es_subcontractor_certificate/i18n/es_CR.po
odoo/addons/l10n_es_subcontractor_certificate/i18n/eu.po
odoo/addons/l10n_es_subcontractor_certificate/i18n/fr.po
odoo/addons/l10n_es_subcontractor_certificate/i18n/gl.po
odoo/addons/l10n_es_subcontractor_certificate/i18n/hr.po
odoo/addons/l10n_es_subcontractor_certificate/i18n/l10n_es_subcontractor_certificate.pot
odoo/addons/l10n_es_subcontractor_certificate/i18n/nl.po
odoo/addons/l10n_es_subcontractor_certificate/i18n/pl.po
odoo/addons/l10n_es_subcontractor_certificate/i18n/pt.po
odoo/addons/l10n_es_subcontractor_certificate/i18n/pt_BR.po
odoo/addons/l10n_es_subcontractor_certificate/i18n/ru.po
odoo/addons/l10n_es_subcontractor_certificate/i18n/sl.po
odoo/addons/l10n_es_subcontractor_certificate/i18n/sv.po
odoo/addons/l10n_es_subcontractor_certificate/i18n/tr.po
odoo/addons/l10n_es_subcontractor_certificate/i18n/vi.po
odoo/addons/l10n_es_subcontractor_certificate/models/__init__.py
odoo/addons/l10n_es_subcontractor_certificate/models/subcontractor_certificate.py
odoo/addons/l10n_es_subcontractor_certificate/readme/CONTRIBUTORS.rst
odoo/addons/l10n_es_subcontractor_certificate/readme/DESCRIPTION.rst
odoo/addons/l10n_es_subcontractor_certificate/static/description/icon.png
odoo/addons/l10n_es_subcontractor_certificate/static/description/index.html
odoo/addons/l10n_es_subcontractor_certificate/tests/__init__.py
odoo/addons/l10n_es_subcontractor_certificate/tests/test_l10n_es_subcontractor_certificate.py
odoo12_addon_l10n_es_subcontractor_certificate-12.0.1.0.0.99.dev7.dist-info/METADATA
odoo12_addon_l10n_es_subcontractor_certificate-12.0.1.0.0.99.dev7.dist-info/WHEEL
odoo12_addon_l10n_es_subcontractor_certificate-12.0.1.0.0.99.dev7.dist-info/top_level.txt
odoo12_addon_l10n_es_subcontractor_certificate-12.0.1.0.0.99.dev7.dist-info/RECORD
